dapp_api/__init__.py
dapp_api/api.py
dapp_api/fragments/EntityDetail.py
dapp_api/fragments/EntityLink.py
dapp_api/fragments/PredicateDetails.py
dapp_api/fragments/TripleWidget.py
dapp_api/fragments/__init__.py
dapp_api/queries/AddTripleToEntityById.py
dapp_api/queries/AdminTemplates.py
dapp_api/queries/Authenticate.py
dapp_api/queries/CreateEntity.py
dapp_api/queries/CreateValidation.py
dapp_api/queries/CurrentUserBlockchainData.py
dapp_api/queries/CurrentUserValidations.py
dapp_api/queries/EntityByName.py
dapp_api/queries/EntityDetail.py
dapp_api/queries/EntityGolden.py
dapp_api/queries/EntitySearch.py
dapp_api/queries/FulfillTripleRequest.py
dapp_api/queries/GetAuthenticationMessage.py
dapp_api/queries/GetCurrentUser.py
dapp_api/queries/GetEntities.py
dapp_api/queries/GetPendingTripleRequest.py
dapp_api/queries/GetTripleForValidation.py
dapp_api/queries/Leaderboard.py
dapp_api/queries/LiveView.py
dapp_api/queries/Predicate.py
dapp_api/queries/PredicatesIPFS.py
dapp_api/queries/Templates.py
dapp_api/queries/TripleCount.py
dapp_api/queries/__init__.py
dapp_api/query.py
dapp_api/schema.py
dapp_api-0.0.3.dist-info/WHEEL
dapp_api-0.0.3.dist-info/METADATA
dapp_api-0.0.3.dist-info/RECORD
