Metadata-Version: 2.1
Name: dapp-api
Version: 0.0.3
Summary: Golden's Python wrapper for the dApp GraphQL API
Author: aychang95
Requires-Python: >=3.8,<4.0
Classifier: Programming Language :: Python :: 3
Classifier: Programming Language :: Python :: 3.10
Classifier: Programming Language :: Python :: 3.8
Classifier: Programming Language :: Python :: 3.9
Provides-Extra: data-tools
Provides-Extra: docs
Provides-Extra: web3
Requires-Dist: ipywidgets (>=7.6.3,<8.0.0); extra == "data-tools"
Requires-Dist: jupyterlab (>=3.0.0,<4.0.0); extra == "data-tools"
Requires-Dist: mkdocs (>=1.3.0,<2.0.0)
Requires-Dist: mkdocs-jupyter (>=0.20.1,<0.21.0); extra == "docs"
Requires-Dist: mkdocs-material (>=8.2.9,<9.0.0); extra == "docs"
Requires-Dist: mkdocstrings (>=0.18.1,<0.19.0); extra == "docs"
Requires-Dist: numpy (>=1.22.3,<2.0.0); extra == "data-tools"
Requires-Dist: pandas (>=1.4.1,<2.0.0); extra == "data-tools"
Requires-Dist: requests (>=2.27.1,<3.0.0)
Requires-Dist: sgqlc (>=16.0,<17.0)
Requires-Dist: tqdm (>=4.63.1,<5.0.0)
Requires-Dist: web3 (>=5.28.0,<6.0.0); extra == "web3"
Requires-Dist: wheel (>=0.36.2,<0.37.0)
